PandaTTex
README.md
setup.py
PandaTTex/__init__.py
PandaTTex/hello.py
PandaTTex.egg-info/PKG-INFO
PandaTTex.egg-info/SOURCES.txt
PandaTTex.egg-info/dependency_links.txt
PandaTTex.egg-info/requires.txt
PandaTTex.egg-info/top_level.txt