Metadata-Version: 2.1
Name: PandaTTex
Version: 0.0.1
Summary: A basic Panda package
Home-page: https://github.com/javatechy/dokr
Author: Marcelo Kenji Noda
Author-email: nodamarcelokenjinoda@gmail.com
License: UNKNOWN
Platform: UNKNOWN
Classifier: Programming Language :: Python :: 3
Classifier: License :: OSI Approved :: MIT License
Classifier: Operating System :: OS Independent
